odoo/addons/document_page_environmental_aspect/README.rst
odoo/addons/document_page_environmental_aspect/__init__.py
odoo/addons/document_page_environmental_aspect/__manifest__.py
odoo/addons/document_page_environmental_aspect/data/document_page.xml
odoo/addons/document_page_environmental_aspect/i18n/de.po
odoo/addons/document_page_environmental_aspect/i18n/document_page_environmental_aspect.pot
odoo/addons/document_page_environmental_aspect/i18n/es_CL.po
odoo/addons/document_page_environmental_aspect/i18n/fr.po
odoo/addons/document_page_environmental_aspect/i18n/nb.po
odoo/addons/document_page_environmental_aspect/i18n/pt_BR.po
odoo/addons/document_page_environmental_aspect/i18n/sl.po
odoo/addons/document_page_environmental_aspect/i18n/sv.po
odoo/addons/document_page_environmental_aspect/i18n/vi.po
odoo/addons/document_page_environmental_aspect/readme/CONFIGURE.rst
odoo/addons/document_page_environmental_aspect/readme/CONTRIBUTORS.rst
odoo/addons/document_page_environmental_aspect/readme/DESCRIPTION.rst
odoo/addons/document_page_environmental_aspect/readme/USAGE.rst
odoo/addons/document_page_environmental_aspect/static/description/icon.png
odoo/addons/document_page_environmental_aspect/static/description/index.html
odoo/addons/document_page_environmental_aspect/views/document_page.xml
odoo13_addon_document_page_environmental_aspect-13.0.1.0.1.dist-info/METADATA
odoo13_addon_document_page_environmental_aspect-13.0.1.0.1.dist-info/WHEEL
odoo13_addon_document_page_environmental_aspect-13.0.1.0.1.dist-info/top_level.txt
odoo13_addon_document_page_environmental_aspect-13.0.1.0.1.dist-info/RECORD
