Metadata-Version: 2.1
Name: odoo13-addon-document-page-environmental-aspect
Version: 13.0.1.0.1
Summary: Environmental Aspects
Home-page: http://www.savoirfairelinux.com
Author: Savoir-faire Linux, Odoo Community Association (OCA)
Author-email: support@odoo-community.org
License: AGPL-3
Platform: UNKNOWN
Classifier: Programming Language :: Python
Classifier: Framework :: Odoo
Classifier: License :: OSI Approved :: GNU Affero General Public License v3
Requires-Python: >=3.5
Requires-Dist: odoo13-addon-document-page
Requires-Dist: odoo13-addon-mgmtsystem
Requires-Dist: odoo (<13.1dev,>=13.0a)
